protect_rm/__init__.py
protect_rm/config.py
protect_rm/protect.py
protect_rm/rm_p.py
protect_rm-0.1.5.dist-info/LICENSE
protect_rm-0.1.5.dist-info/METADATA
protect_rm-0.1.5.dist-info/WHEEL
protect_rm-0.1.5.dist-info/entry_points.txt
protect_rm-0.1.5.dist-info/top_level.txt
protect_rm-0.1.5.dist-info/RECORD
