Metadata-Version: 2.1
Name: protect-rm
Version: 0.1.5
Summary: A modified version of rm-protection (https://pypi.org/project/rm-protection/) with some new implementation. Mainly for myself.
Home-page: UNKNOWN
Author: Sam Sheng
Author-email: sam_sheng@outlook.com
License: MIT
Platform: UNKNOWN
Classifier: Programming Language :: Python :: 3
Classifier: License :: OSI Approved :: MIT License
Classifier: Operating System :: OS Independent
